[
  {
    "_id": "198ac6d0-bd1c-11e9-9d50-13fde21eb130",
    "_type": "visualization",
    "_source": {
      "title": "[rucio] Data per site",
      "visState": "{\"title\":\"[rucio] Data per site\",\"type\":\"table\",\"params\":{\"perPage\":10,\"showPartialRows\":false,\"showMetricsAtAllLevels\":false,\"sort\":{\"columnIndex\":null,\"direction\":null},\"showTotal\":false,\"totalFunc\":\"sum\"},\"aggs\":[{\"id\":\"1\",\"enabled\":true,\"type\":\"sum\",\"schema\":\"metric\",\"params\":{\"field\":\"used\",\"customLabel\":\"Total bytes\"}},{\"id\":\"2\",\"enabled\":true,\"type\":\"sum\",\"schema\":\"metric\",\"params\":{\"field\":\"files\",\"customLabel\":\"Files\"}},{\"id\":\"3\",\"enabled\":true,\"type\":\"terms\",\"schema\":\"bucket\",\"params\":{\"field\":\"rse.keyword\",\"size\":9,\"order\":\"desc\",\"orderBy\":\"1\",\"otherBucket\":false,\"otherBucketLabel\":\"Other\",\"missingBucket\":false,\"missingBucketLabel\":\"Missing\",\"customLabel\":\"rse\"}}]}",
      "uiStateJSON": "{\"vis\":{\"params\":{\"sort\":{\"columnIndex\":null,\"direction\":null}}}}",
      "description": "",
      "version": 1,
      "kibanaSavedObjectMeta": {
        "searchSourceJSON": "{\"query\":{\"query\":\"\",\"language\":\"kuery\"},\"filter\":[],\"indexRefName\":\"kibanaSavedObjectMeta.searchSourceJSON.index\"}"
      }
    },
    "_migrationVersion": {
      "visualization": "7.0.1"
    },
    "_references": [
      {
        "name": "kibanaSavedObjectMeta.searchSourceJSON.index",
        "type": "index-pattern",
        "id": "d1018b60-b519-11e9-9d50-13fde21eb130"
      }
    ]
  }
]
